{
    "directed": false,
    "graph": {},
    "links": [
        {
            "source": "Sant Juli\u00e0 de L\u00f2ria",
            "target": "Sant Juli\u00e0 de L\u00f2ria",
            "weight": 3
        },
        {
            "source": "Sant Juli\u00e0 de L\u00f2ria",
            "target": "Gokwe",
            "weight": 9
        },
        {
            "source": "Sant Juli\u00e0 de L\u00f2ria",
            "target": "Glendale",
            "weight": 1
        },
        {
            "source": "Sant Juli\u00e0 de L\u00f2ria",
            "target": "Filabusi",
            "weight": 2
        },
        {
            "source": "Sant Juli\u00e0 de L\u00f2ria",
            "target": "Esigodini",
            "weight": 5
        },
        {
            "source": "Sant Juli\u00e0 de L\u00f2ria",
            "target": "Dorowa Mining Lease",
            "weight": 6
        },
        {
            "source": "Sant Juli\u00e0 de L\u00f2ria",
            "target": "Dete",
            "weight": 8
        },
        {
            "source": "Sant Juli\u00e0 de L\u00f2ria",
            "target": "Concession",
            "weight": 5
        },
        {
            "source": "Sant Juli\u00e0 de L\u00f2ria",
            "target": "Chivhu",
            "weight": 6
        },
        {
            "source": "Sant Juli\u00e0 de L\u00f2ria",
            "target": "Chirundu",
            "weight": 8
        },
        {
            "source": "Sant Juli\u00e0 de L\u00f2ria",
            "target": "Chiredzi",
            "weight": 8
        },
        {
            "source": "Sant Juli\u00e0 de L\u00f2ria",
            "target": "Chipinge",
            "weight": 7
        },
        {
            "source": "Sant Juli\u00e0 de L\u00f2ria",
            "target": "Chinhoyi",
            "weight": 4
        },
        {
            "source": "Sant Juli\u00e0 de L\u00f2ria",
            "target": "Chimanimani",
            "weight": 3
        },
        {
            "source": "Sant Juli\u00e0 de L\u00f2ria",
            "target": "Chegutu",
            "weight": 1
        },
        {
            "source": "Sant Juli\u00e0 de L\u00f2ria",
            "target": "Chakari",
            "weight": 10
        },
        {
            "source": "Sant Juli\u00e0 de L\u00f2ria",
            "target": "Centenary",
            "weight": 3
        },
        {
            "source": "Sant Juli\u00e0 de L\u00f2ria",
            "target": "Bulawayo",
            "weight": 4
        },
        {
            "source": "Sant Juli\u00e0 de L\u00f2ria",
            "target": "Binga",
            "weight": 6
        },
        {
            "source": "Sant Juli\u00e0 de L\u00f2ria",
            "target": "Bindura",
            "weight": 6
        },
        {
            "source": "Sant Juli\u00e0 de L\u00f2ria",
            "target": "Beitbridge",
            "weight": 10
        },
        {
            "source": "Sant Juli\u00e0 de L\u00f2ria",
            "target": "Beatrice",
            "weight": 1
        },
        {
            "source": "Sant Juli\u00e0 de L\u00f2ria",
            "target": "Banket",
            "weight": 8
        },
        {
            "source": "Sant Juli\u00e0 de L\u00f2ria",
            "target": "Epworth",
            "weight": 4
        },
        {
            "source": "Sant Juli\u00e0 de L\u00f2ria",
            "target": "Chitungwiza",
            "weight": 4
        },
        {
            "source": "Gokwe",
            "target": "Gokwe",
            "weight": 8
        },
        {
            "source": "Gokwe",
            "target": "Glendale",
            "weight": 1
        },
        {
            "source": "Gokwe",
            "target": "Filabusi",
            "weight": 1
        },
        {
            "source": "Gokwe",
            "target": "Esigodini",
            "weight": 5
        },
        {
            "source": "Gokwe",
            "target": "Dorowa Mining Lease",
            "weight": 3
        },
        {
            "source": "Gokwe",
            "target": "Dete",
            "weight": 7
        },
        {
            "source": "Gokwe",
            "target": "Concession",
            "weight": 10
        },
        {
            "source": "Gokwe",
            "target": "Chivhu",
            "weight": 10
        },
        {
            "source": "Gokwe",
            "target": "Chirundu",
            "weight": 1
        },
        {
            "source": "Gokwe",
            "target": "Chiredzi",
            "weight": 1
        },
        {
            "source": "Gokwe",
            "target": "Chipinge",
            "weight": 8
        },
        {
            "source": "Gokwe",
            "target": "Chinhoyi",
            "weight": 9
        },
        {
            "source": "Gokwe",
            "target": "Chimanimani",
            "weight": 4
        },
        {
            "source": "Gokwe",
            "target": "Chegutu",
            "weight": 6
        },
        {
            "source": "Gokwe",
            "target": "Chakari",
            "weight": 10
        },
        {
            "source": "Gokwe",
            "target": "Centenary",
            "weight": 7
        },
        {
            "source": "Gokwe",
            "target": "Bulawayo",
            "weight": 4
        },
        {
            "source": "Gokwe",
            "target": "Binga",
            "weight": 7
        },
        {
            "source": "Gokwe",
            "target": "Bindura",
            "weight": 2
        },
        {
            "source": "Gokwe",
            "target": "Beitbridge",
            "weight": 9
        },
        {
            "source": "Gokwe",
            "target": "Beatrice",
            "weight": 8
        },
        {
            "source": "Gokwe",
            "target": "Banket",
            "weight": 10
        },
        {
            "source": "Gokwe",
            "target": "Epworth",
            "weight": 8
        },
        {
            "source": "Gokwe",
            "target": "Chitungwiza",
            "weight": 9
        },
        {
            "source": "Glendale",
            "target": "Glendale",
            "weight": 6
        },
        {
            "source": "Glendale",
            "target": "Filabusi",
            "weight": 6
        },
        {
            "source": "Glendale",
            "target": "Esigodini",
            "weight": 10
        },
        {
            "source": "Glendale",
            "target": "Dorowa Mining Lease",
            "weight": 5
        },
        {
            "source": "Glendale",
            "target": "Dete",
            "weight": 10
        },
        {
            "source": "Glendale",
            "target": "Concession",
            "weight": 10
        },
        {
            "source": "Glendale",
            "target": "Chivhu",
            "weight": 2
        },
        {
            "source": "Glendale",
            "target": "Chirundu",
            "weight": 9
        },
        {
            "source": "Glendale",
            "target": "Chiredzi",
            "weight": 2
        },
        {
            "source": "Glendale",
            "target": "Chipinge",
            "weight": 3
        },
        {
            "source": "Glendale",
            "target": "Chinhoyi",
            "weight": 7
        },
        {
            "source": "Glendale",
            "target": "Chimanimani",
            "weight": 9
        },
        {
            "source": "Glendale",
            "target": "Chegutu",
            "weight": 3
        },
        {
            "source": "Glendale",
            "target": "Chakari",
            "weight": 6
        },
        {
            "source": "Glendale",
            "target": "Centenary",
            "weight": 9
        },
        {
            "source": "Glendale",
            "target": "Bulawayo",
            "weight": 7
        },
        {
            "source": "Glendale",
            "target": "Binga",
            "weight": 5
        },
        {
            "source": "Glendale",
            "target": "Bindura",
            "weight": 1
        },
        {
            "source": "Glendale",
            "target": "Beitbridge",
            "weight": 5
        },
        {
            "source": "Glendale",
            "target": "Beatrice",
            "weight": 7
        },
        {
            "source": "Glendale",
            "target": "Banket",
            "weight": 8
        },
        {
            "source": "Glendale",
            "target": "Epworth",
            "weight": 4
        },
        {
            "source": "Glendale",
            "target": "Chitungwiza",
            "weight": 3
        },
        {
            "source": "Filabusi",
            "target": "Filabusi",
            "weight": 10
        },
        {
            "source": "Filabusi",
            "target": "Esigodini",
            "weight": 4
        },
        {
            "source": "Filabusi",
            "target": "Dorowa Mining Lease",
            "weight": 5
        },
        {
            "source": "Filabusi",
            "target": "Dete",
            "weight": 1
        },
        {
            "source": "Filabusi",
            "target": "Concession",
            "weight": 3
        },
        {
            "source": "Filabusi",
            "target": "Chivhu",
            "weight": 1
        },
        {
            "source": "Filabusi",
            "target": "Chirundu",
            "weight": 6
        },
        {
            "source": "Filabusi",
            "target": "Chiredzi",
            "weight": 6
        },
        {
            "source": "Filabusi",
            "target": "Chipinge",
            "weight": 9
        },
        {
            "source": "Filabusi",
            "target": "Chinhoyi",
            "weight": 3
        },
        {
            "source": "Filabusi",
            "target": "Chimanimani",
            "weight": 8
        },
        {
            "source": "Filabusi",
            "target": "Chegutu",
            "weight": 1
        },
        {
            "source": "Filabusi",
            "target": "Chakari",
            "weight": 7
        },
        {
            "source": "Filabusi",
            "target": "Centenary",
            "weight": 1
        },
        {
            "source": "Filabusi",
            "target": "Bulawayo",
            "weight": 7
        },
        {
            "source": "Filabusi",
            "target": "Binga",
            "weight": 9
        },
        {
            "source": "Filabusi",
            "target": "Bindura",
            "weight": 6
        },
        {
            "source": "Filabusi",
            "target": "Beitbridge",
            "weight": 5
        },
        {
            "source": "Filabusi",
            "target": "Beatrice",
            "weight": 4
        },
        {
            "source": "Filabusi",
            "target": "Banket",
            "weight": 2
        },
        {
            "source": "Filabusi",
            "target": "Epworth",
            "weight": 10
        },
        {
            "source": "Filabusi",
            "target": "Chitungwiza",
            "weight": 6
        },
        {
            "source": "Esigodini",
            "target": "Esigodini",
            "weight": 5
        },
        {
            "source": "Esigodini",
            "target": "Dorowa Mining Lease",
            "weight": 2
        },
        {
            "source": "Esigodini",
            "target": "Dete",
            "weight": 6
        },
        {
            "source": "Esigodini",
            "target": "Concession",
            "weight": 1
        },
        {
            "source": "Esigodini",
            "target": "Chivhu",
            "weight": 3
        },
        {
            "source": "Esigodini",
            "target": "Chirundu",
            "weight": 4
        },
        {
            "source": "Esigodini",
            "target": "Chiredzi",
            "weight": 7
        },
        {
            "source": "Esigodini",
            "target": "Chipinge",
            "weight": 9
        },
        {
            "source": "Esigodini",
            "target": "Chinhoyi",
            "weight": 4
        },
        {
            "source": "Esigodini",
            "target": "Chimanimani",
            "weight": 7
        },
        {
            "source": "Esigodini",
            "target": "Chegutu",
            "weight": 8
        },
        {
            "source": "Esigodini",
            "target": "Chakari",
            "weight": 1
        },
        {
            "source": "Esigodini",
            "target": "Centenary",
            "weight": 9
        },
        {
            "source": "Esigodini",
            "target": "Bulawayo",
            "weight": 3
        },
        {
            "source": "Esigodini",
            "target": "Binga",
            "weight": 5
        },
        {
            "source": "Esigodini",
            "target": "Bindura",
            "weight": 5
        },
        {
            "source": "Esigodini",
            "target": "Beitbridge",
            "weight": 1
        },
        {
            "source": "Esigodini",
            "target": "Beatrice",
            "weight": 5
        },
        {
            "source": "Esigodini",
            "target": "Banket",
            "weight": 8
        },
        {
            "source": "Esigodini",
            "target": "Epworth",
            "weight": 7
        },
        {
            "source": "Esigodini",
            "target": "Chitungwiza",
            "weight": 9
        },
        {
            "source": "Dorowa Mining Lease",
            "target": "Dorowa Mining Lease",
            "weight": 5
        },
        {
            "source": "Dorowa Mining Lease",
            "target": "Dete",
            "weight": 8
        },
        {
            "source": "Dorowa Mining Lease",
            "target": "Concession",
            "weight": 8
        },
        {
            "source": "Dorowa Mining Lease",
            "target": "Chivhu",
            "weight": 4
        },
        {
            "source": "Dorowa Mining Lease",
            "target": "Chirundu",
            "weight": 4
        },
        {
            "source": "Dorowa Mining Lease",
            "target": "Chiredzi",
            "weight": 10
        },
        {
            "source": "Dorowa Mining Lease",
            "target": "Chipinge",
            "weight": 2
        },
        {
            "source": "Dorowa Mining Lease",
            "target": "Chinhoyi",
            "weight": 9
        },
        {
            "source": "Dorowa Mining Lease",
            "target": "Chimanimani",
            "weight": 6
        },
        {
            "source": "Dorowa Mining Lease",
            "target": "Chegutu",
            "weight": 2
        },
        {
            "source": "Dorowa Mining Lease",
            "target": "Chakari",
            "weight": 9
        },
        {
            "source": "Dorowa Mining Lease",
            "target": "Centenary",
            "weight": 3
        },
        {
            "source": "Dorowa Mining Lease",
            "target": "Bulawayo",
            "weight": 8
        },
        {
            "source": "Dorowa Mining Lease",
            "target": "Binga",
            "weight": 4
        },
        {
            "source": "Dorowa Mining Lease",
            "target": "Bindura",
            "weight": 5
        },
        {
            "source": "Dorowa Mining Lease",
            "target": "Beitbridge",
            "weight": 4
        },
        {
            "source": "Dorowa Mining Lease",
            "target": "Beatrice",
            "weight": 1
        },
        {
            "source": "Dorowa Mining Lease",
            "target": "Banket",
            "weight": 1
        },
        {
            "source": "Dorowa Mining Lease",
            "target": "Epworth",
            "weight": 3
        },
        {
            "source": "Dorowa Mining Lease",
            "target": "Chitungwiza",
            "weight": 9
        },
        {
            "source": "Dete",
            "target": "Dete",
            "weight": 9
        },
        {
            "source": "Dete",
            "target": "Concession",
            "weight": 2
        },
        {
            "source": "Dete",
            "target": "Chivhu",
            "weight": 10
        },
        {
            "source": "Dete",
            "target": "Chirundu",
            "weight": 5
        },
        {
            "source": "Dete",
            "target": "Chiredzi",
            "weight": 1
        },
        {
            "source": "Dete",
            "target": "Chipinge",
            "weight": 7
        },
        {
            "source": "Dete",
            "target": "Chinhoyi",
            "weight": 3
        },
        {
            "source": "Dete",
            "target": "Chimanimani",
            "weight": 10
        },
        {
            "source": "Dete",
            "target": "Chegutu",
            "weight": 3
        },
        {
            "source": "Dete",
            "target": "Chakari",
            "weight": 2
        },
        {
            "source": "Dete",
            "target": "Centenary",
            "weight": 5
        },
        {
            "source": "Dete",
            "target": "Bulawayo",
            "weight": 3
        },
        {
            "source": "Dete",
            "target": "Binga",
            "weight": 10
        },
        {
            "source": "Dete",
            "target": "Bindura",
            "weight": 7
        },
        {
            "source": "Dete",
            "target": "Beitbridge",
            "weight": 3
        },
        {
            "source": "Dete",
            "target": "Beatrice",
            "weight": 6
        },
        {
            "source": "Dete",
            "target": "Banket",
            "weight": 1
        },
        {
            "source": "Dete",
            "target": "Epworth",
            "weight": 10
        },
        {
            "source": "Dete",
            "target": "Chitungwiza",
            "weight": 1
        },
        {
            "source": "Concession",
            "target": "Concession",
            "weight": 10
        },
        {
            "source": "Concession",
            "target": "Chivhu",
            "weight": 3
        },
        {
            "source": "Concession",
            "target": "Chirundu",
            "weight": 9
        },
        {
            "source": "Concession",
            "target": "Chiredzi",
            "weight": 6
        },
        {
            "source": "Concession",
            "target": "Chipinge",
            "weight": 6
        },
        {
            "source": "Concession",
            "target": "Chinhoyi",
            "weight": 7
        },
        {
            "source": "Concession",
            "target": "Chimanimani",
            "weight": 8
        },
        {
            "source": "Concession",
            "target": "Chegutu",
            "weight": 7
        },
        {
            "source": "Concession",
            "target": "Chakari",
            "weight": 10
        },
        {
            "source": "Concession",
            "target": "Centenary",
            "weight": 9
        },
        {
            "source": "Concession",
            "target": "Bulawayo",
            "weight": 10
        },
        {
            "source": "Concession",
            "target": "Binga",
            "weight": 7
        },
        {
            "source": "Concession",
            "target": "Bindura",
            "weight": 2
        },
        {
            "source": "Concession",
            "target": "Beitbridge",
            "weight": 2
        },
        {
            "source": "Concession",
            "target": "Beatrice",
            "weight": 10
        },
        {
            "source": "Concession",
            "target": "Banket",
            "weight": 2
        },
        {
            "source": "Concession",
            "target": "Epworth",
            "weight": 8
        },
        {
            "source": "Concession",
            "target": "Chitungwiza",
            "weight": 1
        },
        {
            "source": "Chivhu",
            "target": "Chivhu",
            "weight": 5
        },
        {
            "source": "Chivhu",
            "target": "Chirundu",
            "weight": 10
        },
        {
            "source": "Chivhu",
            "target": "Chiredzi",
            "weight": 7
        },
        {
            "source": "Chivhu",
            "target": "Chipinge",
            "weight": 7
        },
        {
            "source": "Chivhu",
            "target": "Chinhoyi",
            "weight": 3
        },
        {
            "source": "Chivhu",
            "target": "Chimanimani",
            "weight": 7
        },
        {
            "source": "Chivhu",
            "target": "Chegutu",
            "weight": 2
        },
        {
            "source": "Chivhu",
            "target": "Chakari",
            "weight": 6
        },
        {
            "source": "Chivhu",
            "target": "Centenary",
            "weight": 10
        },
        {
            "source": "Chivhu",
            "target": "Bulawayo",
            "weight": 8
        },
        {
            "source": "Chivhu",
            "target": "Binga",
            "weight": 6
        },
        {
            "source": "Chivhu",
            "target": "Bindura",
            "weight": 3
        },
        {
            "source": "Chivhu",
            "target": "Beitbridge",
            "weight": 8
        },
        {
            "source": "Chivhu",
            "target": "Beatrice",
            "weight": 5
        },
        {
            "source": "Chivhu",
            "target": "Banket",
            "weight": 2
        },
        {
            "source": "Chivhu",
            "target": "Epworth",
            "weight": 7
        },
        {
            "source": "Chivhu",
            "target": "Chitungwiza",
            "weight": 4
        },
        {
            "source": "Chirundu",
            "target": "Chirundu",
            "weight": 10
        },
        {
            "source": "Chirundu",
            "target": "Chiredzi",
            "weight": 7
        },
        {
            "source": "Chirundu",
            "target": "Chipinge",
            "weight": 4
        },
        {
            "source": "Chirundu",
            "target": "Chinhoyi",
            "weight": 5
        },
        {
            "source": "Chirundu",
            "target": "Chimanimani",
            "weight": 8
        },
        {
            "source": "Chirundu",
            "target": "Chegutu",
            "weight": 10
        },
        {
            "source": "Chirundu",
            "target": "Chakari",
            "weight": 7
        },
        {
            "source": "Chirundu",
            "target": "Centenary",
            "weight": 7
        },
        {
            "source": "Chirundu",
            "target": "Bulawayo",
            "weight": 9
        },
        {
            "source": "Chirundu",
            "target": "Binga",
            "weight": 1
        },
        {
            "source": "Chirundu",
            "target": "Bindura",
            "weight": 6
        },
        {
            "source": "Chirundu",
            "target": "Beitbridge",
            "weight": 2
        },
        {
            "source": "Chirundu",
            "target": "Beatrice",
            "weight": 1
        },
        {
            "source": "Chirundu",
            "target": "Banket",
            "weight": 5
        },
        {
            "source": "Chirundu",
            "target": "Epworth",
            "weight": 1
        },
        {
            "source": "Chirundu",
            "target": "Chitungwiza",
            "weight": 3
        },
        {
            "source": "Chiredzi",
            "target": "Chiredzi",
            "weight": 10
        },
        {
            "source": "Chiredzi",
            "target": "Chipinge",
            "weight": 2
        },
        {
            "source": "Chiredzi",
            "target": "Chinhoyi",
            "weight": 6
        },
        {
            "source": "Chiredzi",
            "target": "Chimanimani",
            "weight": 8
        },
        {
            "source": "Chiredzi",
            "target": "Chegutu",
            "weight": 5
        },
        {
            "source": "Chiredzi",
            "target": "Chakari",
            "weight": 9
        },
        {
            "source": "Chiredzi",
            "target": "Centenary",
            "weight": 9
        },
        {
            "source": "Chiredzi",
            "target": "Bulawayo",
            "weight": 4
        },
        {
            "source": "Chiredzi",
            "target": "Binga",
            "weight": 5
        },
        {
            "source": "Chiredzi",
            "target": "Bindura",
            "weight": 4
        },
        {
            "source": "Chiredzi",
            "target": "Beitbridge",
            "weight": 2
        },
        {
            "source": "Chiredzi",
            "target": "Beatrice",
            "weight": 4
        },
        {
            "source": "Chiredzi",
            "target": "Banket",
            "weight": 9
        },
        {
            "source": "Chiredzi",
            "target": "Epworth",
            "weight": 4
        },
        {
            "source": "Chiredzi",
            "target": "Chitungwiza",
            "weight": 3
        },
        {
            "source": "Chipinge",
            "target": "Chipinge",
            "weight": 3
        },
        {
            "source": "Chipinge",
            "target": "Chinhoyi",
            "weight": 1
        },
        {
            "source": "Chipinge",
            "target": "Chimanimani",
            "weight": 2
        },
        {
            "source": "Chipinge",
            "target": "Chegutu",
            "weight": 8
        },
        {
            "source": "Chipinge",
            "target": "Chakari",
            "weight": 4
        },
        {
            "source": "Chipinge",
            "target": "Centenary",
            "weight": 8
        },
        {
            "source": "Chipinge",
            "target": "Bulawayo",
            "weight": 9
        },
        {
            "source": "Chipinge",
            "target": "Binga",
            "weight": 7
        },
        {
            "source": "Chipinge",
            "target": "Bindura",
            "weight": 1
        },
        {
            "source": "Chipinge",
            "target": "Beitbridge",
            "weight": 8
        },
        {
            "source": "Chipinge",
            "target": "Beatrice",
            "weight": 3
        },
        {
            "source": "Chipinge",
            "target": "Banket",
            "weight": 9
        },
        {
            "source": "Chipinge",
            "target": "Epworth",
            "weight": 10
        },
        {
            "source": "Chipinge",
            "target": "Chitungwiza",
            "weight": 3
        },
        {
            "source": "Chinhoyi",
            "target": "Chinhoyi",
            "weight": 1
        },
        {
            "source": "Chinhoyi",
            "target": "Chimanimani",
            "weight": 7
        },
        {
            "source": "Chinhoyi",
            "target": "Chegutu",
            "weight": 7
        },
        {
            "source": "Chinhoyi",
            "target": "Chakari",
            "weight": 2
        },
        {
            "source": "Chinhoyi",
            "target": "Centenary",
            "weight": 5
        },
        {
            "source": "Chinhoyi",
            "target": "Bulawayo",
            "weight": 10
        },
        {
            "source": "Chinhoyi",
            "target": "Binga",
            "weight": 5
        },
        {
            "source": "Chinhoyi",
            "target": "Bindura",
            "weight": 7
        },
        {
            "source": "Chinhoyi",
            "target": "Beitbridge",
            "weight": 6
        },
        {
            "source": "Chinhoyi",
            "target": "Beatrice",
            "weight": 7
        },
        {
            "source": "Chinhoyi",
            "target": "Banket",
            "weight": 10
        },
        {
            "source": "Chinhoyi",
            "target": "Epworth",
            "weight": 6
        },
        {
            "source": "Chinhoyi",
            "target": "Chitungwiza",
            "weight": 9
        },
        {
            "source": "Chimanimani",
            "target": "Chimanimani",
            "weight": 1
        },
        {
            "source": "Chimanimani",
            "target": "Chegutu",
            "weight": 1
        },
        {
            "source": "Chimanimani",
            "target": "Chakari",
            "weight": 2
        },
        {
            "source": "Chimanimani",
            "target": "Centenary",
            "weight": 2
        },
        {
            "source": "Chimanimani",
            "target": "Bulawayo",
            "weight": 9
        },
        {
            "source": "Chimanimani",
            "target": "Binga",
            "weight": 3
        },
        {
            "source": "Chimanimani",
            "target": "Bindura",
            "weight": 3
        },
        {
            "source": "Chimanimani",
            "target": "Beitbridge",
            "weight": 1
        },
        {
            "source": "Chimanimani",
            "target": "Beatrice",
            "weight": 10
        },
        {
            "source": "Chimanimani",
            "target": "Banket",
            "weight": 7
        },
        {
            "source": "Chimanimani",
            "target": "Epworth",
            "weight": 8
        },
        {
            "source": "Chimanimani",
            "target": "Chitungwiza",
            "weight": 9
        },
        {
            "source": "Chegutu",
            "target": "Chegutu",
            "weight": 6
        },
        {
            "source": "Chegutu",
            "target": "Chakari",
            "weight": 2
        },
        {
            "source": "Chegutu",
            "target": "Centenary",
            "weight": 2
        },
        {
            "source": "Chegutu",
            "target": "Bulawayo",
            "weight": 7
        },
        {
            "source": "Chegutu",
            "target": "Binga",
            "weight": 1
        },
        {
            "source": "Chegutu",
            "target": "Bindura",
            "weight": 6
        },
        {
            "source": "Chegutu",
            "target": "Beitbridge",
            "weight": 10
        },
        {
            "source": "Chegutu",
            "target": "Beatrice",
            "weight": 9
        },
        {
            "source": "Chegutu",
            "target": "Banket",
            "weight": 4
        },
        {
            "source": "Chegutu",
            "target": "Epworth",
            "weight": 7
        },
        {
            "source": "Chegutu",
            "target": "Chitungwiza",
            "weight": 8
        },
        {
            "source": "Chakari",
            "target": "Chakari",
            "weight": 4
        },
        {
            "source": "Chakari",
            "target": "Centenary",
            "weight": 10
        },
        {
            "source": "Chakari",
            "target": "Bulawayo",
            "weight": 8
        },
        {
            "source": "Chakari",
            "target": "Binga",
            "weight": 2
        },
        {
            "source": "Chakari",
            "target": "Bindura",
            "weight": 2
        },
        {
            "source": "Chakari",
            "target": "Beitbridge",
            "weight": 2
        },
        {
            "source": "Chakari",
            "target": "Beatrice",
            "weight": 7
        },
        {
            "source": "Chakari",
            "target": "Banket",
            "weight": 3
        },
        {
            "source": "Chakari",
            "target": "Epworth",
            "weight": 7
        },
        {
            "source": "Chakari",
            "target": "Chitungwiza",
            "weight": 4
        },
        {
            "source": "Centenary",
            "target": "Centenary",
            "weight": 3
        },
        {
            "source": "Centenary",
            "target": "Bulawayo",
            "weight": 5
        },
        {
            "source": "Centenary",
            "target": "Binga",
            "weight": 4
        },
        {
            "source": "Centenary",
            "target": "Bindura",
            "weight": 4
        },
        {
            "source": "Centenary",
            "target": "Beitbridge",
            "weight": 6
        },
        {
            "source": "Centenary",
            "target": "Beatrice",
            "weight": 3
        },
        {
            "source": "Centenary",
            "target": "Banket",
            "weight": 6
        },
        {
            "source": "Centenary",
            "target": "Epworth",
            "weight": 6
        },
        {
            "source": "Centenary",
            "target": "Chitungwiza",
            "weight": 2
        },
        {
            "source": "Bulawayo",
            "target": "Bulawayo",
            "weight": 8
        },
        {
            "source": "Bulawayo",
            "target": "Binga",
            "weight": 2
        },
        {
            "source": "Bulawayo",
            "target": "Bindura",
            "weight": 6
        },
        {
            "source": "Bulawayo",
            "target": "Beitbridge",
            "weight": 3
        },
        {
            "source": "Bulawayo",
            "target": "Beatrice",
            "weight": 3
        },
        {
            "source": "Bulawayo",
            "target": "Banket",
            "weight": 10
        },
        {
            "source": "Bulawayo",
            "target": "Epworth",
            "weight": 3
        },
        {
            "source": "Bulawayo",
            "target": "Chitungwiza",
            "weight": 10
        },
        {
            "source": "Binga",
            "target": "Binga",
            "weight": 6
        },
        {
            "source": "Binga",
            "target": "Bindura",
            "weight": 1
        },
        {
            "source": "Binga",
            "target": "Beitbridge",
            "weight": 5
        },
        {
            "source": "Binga",
            "target": "Beatrice",
            "weight": 7
        },
        {
            "source": "Binga",
            "target": "Banket",
            "weight": 3
        },
        {
            "source": "Binga",
            "target": "Epworth",
            "weight": 1
        },
        {
            "source": "Binga",
            "target": "Chitungwiza",
            "weight": 6
        },
        {
            "source": "Bindura",
            "target": "Bindura",
            "weight": 1
        },
        {
            "source": "Bindura",
            "target": "Beitbridge",
            "weight": 10
        },
        {
            "source": "Bindura",
            "target": "Beatrice",
            "weight": 8
        },
        {
            "source": "Bindura",
            "target": "Banket",
            "weight": 6
        },
        {
            "source": "Bindura",
            "target": "Epworth",
            "weight": 4
        },
        {
            "source": "Bindura",
            "target": "Chitungwiza",
            "weight": 1
        },
        {
            "source": "Beitbridge",
            "target": "Beitbridge",
            "weight": 10
        },
        {
            "source": "Beitbridge",
            "target": "Beatrice",
            "weight": 4
        },
        {
            "source": "Beitbridge",
            "target": "Banket",
            "weight": 2
        },
        {
            "source": "Beitbridge",
            "target": "Epworth",
            "weight": 2
        },
        {
            "source": "Beitbridge",
            "target": "Chitungwiza",
            "weight": 9
        },
        {
            "source": "Beatrice",
            "target": "Beatrice",
            "weight": 6
        },
        {
            "source": "Beatrice",
            "target": "Banket",
            "weight": 1
        },
        {
            "source": "Beatrice",
            "target": "Epworth",
            "weight": 5
        },
        {
            "source": "Beatrice",
            "target": "Chitungwiza",
            "weight": 5
        },
        {
            "source": "Banket",
            "target": "Banket",
            "weight": 8
        },
        {
            "source": "Banket",
            "target": "Epworth",
            "weight": 6
        },
        {
            "source": "Banket",
            "target": "Chitungwiza",
            "weight": 5
        },
        {
            "source": "Epworth",
            "target": "Epworth",
            "weight": 1
        },
        {
            "source": "Epworth",
            "target": "Chitungwiza",
            "weight": 4
        },
        {
            "source": "Chitungwiza",
            "target": "Chitungwiza",
            "weight": 10
        }
    ],
    "multigraph": false,
    "nodes": [
        {
            "id": "Sant Juli\u00e0 de L\u00f2ria"
        },
        {
            "id": "Gokwe"
        },
        {
            "id": "Glendale"
        },
        {
            "id": "Filabusi"
        },
        {
            "id": "Esigodini"
        },
        {
            "id": "Dorowa Mining Lease"
        },
        {
            "id": "Dete"
        },
        {
            "id": "Concession"
        },
        {
            "id": "Chivhu"
        },
        {
            "id": "Chirundu"
        },
        {
            "id": "Chiredzi"
        },
        {
            "id": "Chipinge"
        },
        {
            "id": "Chinhoyi"
        },
        {
            "id": "Chimanimani"
        },
        {
            "id": "Chegutu"
        },
        {
            "id": "Chakari"
        },
        {
            "id": "Centenary"
        },
        {
            "id": "Bulawayo"
        },
        {
            "id": "Binga"
        },
        {
            "id": "Bindura"
        },
        {
            "id": "Beitbridge"
        },
        {
            "id": "Beatrice"
        },
        {
            "id": "Banket"
        },
        {
            "id": "Epworth"
        },
        {
            "id": "Chitungwiza"
        }
    ]
}